srai_openai/__init__.py
srai_openai/client_openai_audio.py
srai_openai/client_openai_chatgpt.py
srai_openai/client_openai_embedding.py
srai_openai/model/__init__.py
srai_openai/model/chatgpt_tool.py
srai_openai/model/prompt_config.py
srai_openai-0.8.2.dist-info/LICENSE.txt
srai_openai-0.8.2.dist-info/METADATA
srai_openai-0.8.2.dist-info/WHEEL
srai_openai-0.8.2.dist-info/RECORD
