Metadata-Version: 2.1
Name: srai-openai
Version: 0.8.2
Summary: A set of functions to better interact with openai.
Home-page: https://github.com/southriverai/srai-openai
License: MIT
Keywords: SRAI,TOOLS
Author: Jaap Oosterbroek
Author-email: jaap.oosterbroek@gmail.com
Requires-Python: >=3.10,<4.0
Classifier: License :: OSI Approved :: MIT License
Classifier: Programming Language :: Python :: 3
Classifier: Programming Language :: Python :: 3.10
Classifier: Programming Language :: Python :: 3.11
Classifier: Programming Language :: Python :: 3.12
Requires-Dist: docstring_parser (>=0.16,<0.17)
Requires-Dist: openai (>=1.35.5,<2.0.0)
Requires-Dist: srai-core (>=0.15.2,<0.16.0)
Requires-Dist: tiktoken (>=0.7,<0.8)
Project-URL: Repository, https://github.com/southriverai/srai-openai
